.codeclimate.yml
.codecov.yml
.coveragerc
.gitignore
.gitlab-ci.yml
LICENSE
MANIFEST.in
Makefile
README.md
VERSION
gitlab-ci-test.sh
manage.py
pytest.ini
requirements.txt
setup.cfg
setup.py
test_settings.py
tox.ini
django_auto_webassets/__init__.py
django_auto_webassets/admin.py
django_auto_webassets/apps.py
django_auto_webassets/models.py
django_auto_webassets/settings.py
django_auto_webassets.egg-info/PKG-INFO
django_auto_webassets.egg-info/SOURCES.txt
django_auto_webassets.egg-info/dependency_links.txt
django_auto_webassets.egg-info/requires.txt
django_auto_webassets.egg-info/top_level.txt
django_auto_webassets/management/__init__.py
django_auto_webassets/management/commands/__init__.py
django_auto_webassets/management/commands/webassetsrequirejs.py
django_auto_webassets/migrations/__init__.py
django_auto_webassets/templates/webassets_tag.html
django_auto_webassets/templatetags/__init__.py
django_auto_webassets/templatetags/auto_webassets.py
django_auto_webassets/tests/__init__.py
django_auto_webassets/tests/conftest.py
django_auto_webassets/tests/package.json
django_auto_webassets/tests/sub_urls_for_test.py
django_auto_webassets/tests/test_functional.py
django_auto_webassets/tests/urls_for_tests.py
django_auto_webassets/tests/assets/__init__.py
django_auto_webassets/tests/assets/assets.py
django_auto_webassets/tests/helpers/__init__.py
django_auto_webassets/tests/helpers/functions.py
django_auto_webassets/tests/static/requirejs_cfg.js
django_auto_webassets/tests/static/css/test_css.css
django_auto_webassets/tests/static/js_for_views/generic.js
django_auto_webassets/tests/static/js_for_views/simple_functional.js
django_auto_webassets/tests/static/js_for_views/simple_functional_alt.js
django_auto_webassets/tests/templates/css_test.html
django_auto_webassets/tests/templates/generic.html
django_auto_webassets/tests/templates/simple_functional.html
django_auto_webassets/tests/views/__init__.py
django_auto_webassets/tests/views/utviews.py
django_auto_webassets/utils/__init__.py
django_auto_webassets/utils/webassetsrjs.py
django_auto_webassets/views/__init__.py
django_auto_webassets/views/mixins.py
doc/Makefile
doc/make.bat
doc/source/conf.py
doc/source/index.rst
doc/source/links.rst
