Metadata-Version: 2.1
Name: django-auto-webassets
Version: 0.0.6
Summary: Convenience Django Template Tags for handling javascript webassests
Home-page: https://gitlab.com/thht_django/django-auto-webassets
Author: Thomas Hartmann
Author-email: thomas.hartmann@th-ht.de
License: GPLv3
Keywords: Django webassets
Platform: UNKNOWN
Classifier: Development Status :: 4 - Beta
Classifier: Framework :: Django
Classifier: Intended Audience :: Developers
Classifier: License :: OSI Approved :: GNU General Public License v3 (GPLv3)
Classifier: Operating System :: OS Independent
Classifier: Programming Language :: Python
